AUTHORS
LICENSE
MANIFEST.in
README.rst
setup.cfg
setup.py
django_textblocks.egg-info/PKG-INFO
django_textblocks.egg-info/SOURCES.txt
django_textblocks.egg-info/dependency_links.txt
django_textblocks.egg-info/requires.txt
django_textblocks.egg-info/top_level.txt
textblocks/__init__.py
textblocks/admin.py
textblocks/conf.py
textblocks/forms.py
textblocks/models.py
textblocks/translation.py
textblocks/utils.py
textblocks/widgets.py
textblocks/templates/textblocks/texthtml.html
textblocks/templatetags/__init__.py
textblocks/templatetags/textblock_tags.py